{
  "$schema": "https://json-schema.org/draft/2020-12/schema",
  "$id": "https://raw.githubusercontent.com/api-evangelist/amazon-mediastore/refs/heads/main/json-schema/mediastore-api-get-cors-policy-output-schema.json",
  "title": "GetCorsPolicyOutput",
  "description": "GetCorsPolicyOutput schema from Amazon MediaStore API",
  "type": "object",
  "properties": {
    "CorsPolicy": {
      "allOf": [
        {
          "$ref": "#/components/schemas/CorsPolicy"
        },
        {
          "description": "The CORS policy assigned to the container."
        }
      ]
    }
  },
  "required": [
    "CorsPolicy"
  ]
}